<annotation>
	<folder>&#36817;</folder>
	<filename>1683171652314.jpg</filename>
	<path>C:\Users\Administrator\Desktop\&#36817;\1683171652314.jpg</path>
	<source>
		<database>Unknown</database>
	</source>
	<size>
		<width>640</width>
		<height>360</height>
		<depth>3</depth>
	</size>
	<segmented>0</segmented>
	<object>
		<name>people</name>
		<pose>Unspecified</pose>
		<truncated>0</truncated>
		<difficult>0</difficult>
		<bndbox>
			<xmin>425</xmin>
			<ymin>106</ymin>
			<xmax>448</xmax>
			<ymax>185</ymax>
		</bndbox>
	</object>
	<object>
		<name>window</name>
		<pose>Unspecified</pose>
		<truncated>0</truncated>
		<difficult>0</difficult>
		<bndbox>
			<xmin>371</xmin>
			<ymin>63</ymin>
			<xmax>453</xmax>
			<ymax>181</ymax>
		</bndbox>
	</object>
</annotation>